[
  {
    "date": "2018-01",
    "states": {
      "AC": 0,
      "AL": 0,
      "AP": 0,
      "AM": 0,
      "BA": 0,
      "CE": 0,
      "DF": 0,
      "ES": 0,
      "GO": 0,
      "MA": 0,
      "MT": 0,
      "MS": 0,
      "MG": 0,
      "PA": 0,
      "PB": 0,
      "PR": 0,
      "PE": 4,
      "PI": 0,
      "RJ": 0,
      "RN": 0,
      "RS": 0,
      "RO": 0,
      "RR": 0,
      "SC": 0,
      "SP": 0,
      "SE": 0,
      "TO": 0
    }
  },
  {
    "date": "2018-02",
    "states": {
      "AC": 0,
      "AL": 0,
      "AP": 0,
      "AM": 0,
      "BA": 0,
      "CE": 0,
      "DF": 0,
      "ES": 0,
      "GO": 0,
      "MA": 0,
      "MT": 0,
      "MS": 0,
      "MG": 0,
      "PA": 0,
      "PB": 0,
      "PR": 0,
      "PE": 5,
      "PI": 0,
      "RJ": 0,
      "RN": 0,
      "RS": 0,
      "RO": 0,
      "RR": 0,
      "SC": 0,
      "SP": 0,
      "SE": 0,
      "TO": 0
    }
  },
  {
    "date": "2018-03",
    "states": {
      "AC": 0,
      "AL": 0,
      "AP": 0,
      "AM": 0,
      "BA": 0,
      "CE": 0,
      "DF": 0,
      "ES": 0,
      "GO": 0,
      "MA": 0,
      "MT": 0,
      "MS": 0,
      "MG": 0,
      "PA": 0,
      "PB": 0,
      "PR": 0,
      "PE": 6,
      "PI": 0,
      "RJ": 0,
      "RN": 0,
      "RS": 0,
      "RO": 0,
      "RR": 0,
      "SC": 0,
      "SP": 0,
      "SE": 0,
      "TO": 0
    }
  },
  {
    "date": "2018-04",
    "states": {
      "AC": 0,
      "AL": 0,
      "AP": 0,
      "AM": 0,
      "BA": 0,
      "CE": 0,
      "DF": 0,
      "ES": 0,
      "GO": 0,
      "MA": 0,
      "MT": 0,
      "MS": 0,
      "MG": 0,
      "PA": 0,
      "PB": 0,
      "PR": 0,
      "PE": 4,
      "PI": 0,
      "RJ": 0,
      "RN": 0,
      "RS": 0,
      "RO": 0,
      "RR": 0,
      "SC": 0,
      "SP": 0,
      "SE": 0,
      "TO": 0
    }
  },
  {
    "date": "2018-05",
    "states": {
      "AC": 0,
      "AL": 0,
      "AP": 0,
      "AM": 0,
      "BA": 4,
      "CE": 0,
      "DF": 0,
      "ES": 0,
      "GO": 0,
      "MA": 0,
      "MT": 0,
      "MS": 0,
      "MG": 7,
      "PA": 0,
      "PB": 0,
      "PR": 0,
      "PE": 7,
      "PI": 0,
      "RJ": 0,
      "RN": 0,
      "RS": 0,
      "RO": 0,
      "RR": 0,
      "SC": 0,
      "SP": 5,
      "SE": 0,
      "TO": 0
    }
  },
  {
    "date": "2018-06",
    "states": {
      "AC": 0,
      "AL": 0,
      "AP": 0,
      "AM": 0,
      "BA": 0,
      "CE": 4,
      "DF": 0,
      "ES": 0,
      "GO": 0,
      "MA": 0,
      "MT": 0,
      "MS": 0,
      "MG": 0,
      "PA": 0,
      "PB": 7,
      "PR": 0,
      "PE": 8,
      "PI": 0,
      "RJ": 0,
      "RN": 0,
      "RS": 0,
      "RO": 0,
      "RR": 0,
      "SC": 0,
      "SP": 6,
      "SE": 0,
      "TO": 0
    }
  },
  {
    "date": "2018-07",
    "states": {
      "AC": 0,
      "AL": 0,
      "AP": 0,
      "AM": 0,
      "BA": 0,
      "CE": 4,
      "DF": 0,
      "ES": 0,
      "GO": 0,
      "MA": 0,
      "MT": 0,
      "MS": 0,
      "MG": 0,
      "PA": 0,
      "PB": 0,
      "PR": 0,
      "PE": 8,
      "PI": 0,
      "RJ": 0,
      "RN": 0,
      "RS": 0,
      "RO": 0,
      "RR": 0,
      "SC": 0,
      "SP": 0,
      "SE": 0,
      "TO": 0
    }
  },
  {
    "date": "2018-08",
    "states": {
      "AC": 0,
      "AL": 0,
      "AP": 0,
      "AM": 0,
      "BA": 0,
      "CE": 0,
      "DF": 0,
      "ES": 0,
      "GO": 0,
      "MA": 18,
      "MT": 0,
      "MS": 0,
      "MG": 0,
      "PA": 0,
      "PB": 0,
      "PR": 0,
      "PE": 10,
      "PI": 0,
      "RJ": 0,
      "RN": 0,
      "RS": 0,
      "RO": 0,
      "RR": 0,
      "SC": 0,
      "SP": 6,
      "SE": 0,
      "TO": 0
    }
  },
  {
    "date": "2018-09",
    "states": {
      "AC": 0,
      "AL": 0,
      "AP": 0,
      "AM": 0,
      "BA": 3,
      "CE": 5,
      "DF": 0,
      "ES": 0,
      "GO": 0,
      "MA": 0,
      "MT": 0,
      "MS": 0,
      "MG": 0,
      "PA": 0,
      "PB": 0,
      "PR": 0,
      "PE": 6,
      "PI": 0,
      "RJ": 0,
      "RN": 0,
      "RS": 0,
      "RO": 0,
      "RR": 0,
      "SC": 0,
      "SP": 0,
      "SE": 0,
      "TO": 0
    }
  },
  {
    "date": "2018-10",
    "states": {
      "AC": 0,
      "AL": 0,
      "AP": 0,
      "AM": 0,
      "BA": 0,
      "CE": 6,
      "DF": 0,
      "ES": 0,
      "GO": 0,
      "MA": 0,
      "MT": 0,
      "MS": 0,
      "MG": 0,
      "PA": 0,
      "PB": 0,
      "PR": 0,
      "PE": 7,
      "PI": 0,
      "RJ": 0,
      "RN": 0,
      "RS": 0,
      "RO": 0,
      "RR": 0,
      "SC": 0,
      "SP": 0,
      "SE": 0,
      "TO": 58
    }
  },
  {
    "date": "2018-11",
    "states": {
      "AC": 0,
      "AL": 0,
      "AP": 0,
      "AM": 0,
      "BA": 0,
      "CE": 0,
      "DF": 0,
      "ES": 0,
      "GO": 0,
      "MA": 0,
      "MT": 0,
      "MS": 0,
      "MG": 0,
      "PA": 0,
      "PB": 0,
      "PR": 0,
      "PE": 9,
      "PI": 0,
      "RJ": 0,
      "RN": 0,
      "RS": 0,
      "RO": 0,
      "RR": 0,
      "SC": 0,
      "SP": 0,
      "SE": 0,
      "TO": 0
    }
  },
  {
    "date": "2018-12",
    "states": {
      "AC": 0,
      "AL": 0,
      "AP": 0,
      "AM": 0,
      "BA": 0,
      "CE": 6,
      "DF": 0,
      "ES": 0,
      "GO": 0,
      "MA": 0,
      "MT": 0,
      "MS": 0,
      "MG": 0,
      "PA": 0,
      "PB": 0,
      "PR": 0,
      "PE": 10,
      "PI": 0,
      "RJ": 0,
      "RN": 0,
      "RS": 0,
      "RO": 0,
      "RR": 0,
      "SC": 0,
      "SP": 0,
      "SE": 0,
      "TO": 0
    }
  },
  {
    "date": "2019-01",
    "states": {
      "AC": 0,
      "AL": 0,
      "AP": 0,
      "AM": 0,
      "BA": 4,
      "CE": 6,
      "DF": 0,
      "ES": 0,
      "GO": 0,
      "MA": 0,
      "MT": 0,
      "MS": 0,
      "MG": 0,
      "PA": 0,
      "PB": 0,
      "PR": 0,
      "PE": 11,
      "PI": 0,
      "RJ": 0,
      "RN": 0,
      "RS": 0,
      "RO": 0,
      "RR": 0,
      "SC": 0,
      "SP": 5,
      "SE": 0,
      "TO": 0
    }
  },
  {
    "date": "2019-02",
    "states": {
      "AC": 0,
      "AL": 6,
      "AP": 0,
      "AM": 0,
      "BA": 4,
      "CE": 7,
      "DF": 0,
      "ES": 0,
      "GO": 0,
      "MA": 0,
      "MT": 0,
      "MS": 0,
      "MG": 0,
      "PA": 0,
      "PB": 0,
      "PR": 0,
      "PE": 15,
      "PI": 0,
      "RJ": 0,
      "RN": 11,
      "RS": 0,
      "RO": 0,
      "RR": 0,
      "SC": 0,
      "SP": 0,
      "SE": 0,
      "TO": 0
    }
  },
  {
    "date": "2019-03",
    "states": {
      "AC": 0,
      "AL": 11,
      "AP": 0,
      "AM": 0,
      "BA": 6,
      "CE": 9,
      "DF": 0,
      "ES": 0,
      "GO": 0,
      "MA": 0,
      "MT": 0,
      "MS": 0,
      "MG": 0,
      "PA": 0,
      "PB": 13,
      "PR": 0,
      "PE": 19,
      "PI": 0,
      "RJ": 0,
      "RN": 10,
      "RS": 0,
      "RO": 0,
      "RR": 0,
      "SC": 0,
      "SP": 9,
      "SE": 12,
      "TO": 0
    }
  },
  {
    "date": "2019-04",
    "states": {
      "AC": 100,
      "AL": 18,
      "AP": 0,
      "AM": 0,
      "BA": 7,
      "CE": 9,
      "DF": 0,
      "ES": 0,
      "GO": 0,
      "MA": 0,
      "MT": 0,
      "MS": 0,
      "MG": 0,
      "PA": 0,
      "PB": 15,
      "PR": 0,
      "PE": 15,
      "PI": 0,
      "RJ": 0,
      "RN": 0,
      "RS": 0,
      "RO": 0,
      "RR": 0,
      "SC": 0,
      "SP": 4,
      "SE": 0,
      "TO": 0
    }
  },
  {
    "date": "2019-05",
    "states": {
      "AC": 0,
      "AL": 24,
      "AP": 0,
      "AM": 0,
      "BA": 14,
      "CE": 17,
      "DF": 0,
      "ES": 0,
      "GO": 0,
      "MA": 18,
      "MT": 0,
      "MS": 0,
      "MG": 8,
      "PA": 0,
      "PB": 26,
      "PR": 0,
      "PE": 21,
      "PI": 15,
      "RJ": 0,
      "RN": 17,
      "RS": 0,
      "RO": 0,
      "RR": 0,
      "SC": 0,
      "SP": 9,
      "SE": 17,
      "TO": 0
    }
  },
  {
    "date": "2019-06",
    "states": {
      "AC": 0,
      "AL": 38,
      "AP": 0,
      "AM": 0,
      "BA": 27,
      "CE": 38,
      "DF": 0,
      "ES": 0,
      "GO": 0,
      "MA": 39,
      "MT": 0,
      "MS": 0,
      "MG": 18,
      "PA": 22,
      "PB": 29,
      "PR": 29,
      "PE": 43,
      "PI": 38,
      "RJ": 21,
      "RN": 31,
      "RS": 0,
      "RO": 0,
      "RR": 0,
      "SC": 27,
      "SP": 23,
      "SE": 27,
      "TO": 0
    }
  },
  {
    "date": "2019-07",
    "states": {
      "AC": 0,
      "AL": 52,
      "AP": 0,
      "AM": 0,
      "BA": 39,
      "CE": 51,
      "DF": 0,
      "ES": 46,
      "GO": 30,
      "MA": 57,
      "MT": 0,
      "MS": 0,
      "MG": 32,
      "PA": 27,
      "PB": 48,
      "PR": 28,
      "PE": 46,
      "PI": 63,
      "RJ": 24,
      "RN": 51,
      "RS": 0,
      "RO": 0,
      "RR": 0,
      "SC": 52,
      "SP": 24,
      "SE": 53,
      "TO": 0
    }
  },
  {
    "date": "2019-08",
    "states": {
      "AC": 0,
      "AL": 53,
      "AP": 0,
      "AM": 21,
      "BA": 49,
      "CE": 67,
      "DF": 82,
      "ES": 61,
      "GO": 65,
      "MA": 65,
      "MT": 0,
      "MS": 0,
      "MG": 50,
      "PA": 54,
      "PB": 60,
      "PR": 54,
      "PE": 54,
      "PI": 71,
      "RJ": 39,
      "RN": 68,
      "RS": 37,
      "RO": 0,
      "RR": 0,
      "SC": 51,
      "SP": 44,
      "SE": 63,
      "TO": 0
    }
  },
  {
    "date": "2019-09",
    "states": {
      "AC": 0,
      "AL": 73,
      "AP": 0,
      "AM": 44,
      "BA": 75,
      "CE": 71,
      "DF": 100,
      "ES": 48,
      "GO": 48,
      "MA": 94,
      "MT": 92,
      "MS": 78,
      "MG": 62,
      "PA": 71,
      "PB": 69,
      "PR": 44,
      "PE": 61,
      "PI": 84,
      "RJ": 70,
      "RN": 85,
      "RS": 37,
      "RO": 0,
      "RR": 0,
      "SC": 46,
      "SP": 58,
      "SE": 71,
      "TO": 63
    }
  },
  {
    "date": "2019-10",
    "states": {
      "AC": 0,
      "AL": 70,
      "AP": 0,
      "AM": 63,
      "BA": 72,
      "CE": 77,
      "DF": 60,
      "ES": 67,
      "GO": 61,
      "MA": 100,
      "MT": 96,
      "MS": 53,
      "MG": 67,
      "PA": 79,
      "PB": 76,
      "PR": 82,
      "PE": 65,
      "PI": 73,
      "RJ": 67,
      "RN": 79,
      "RS": 66,
      "RO": 0,
      "RR": 0,
      "SC": 89,
      "SP": 71,
      "SE": 81,
      "TO": 59
    }
  },
  {
    "date": "2019-11",
    "states": {
      "AC": 0,
      "AL": 79,
      "AP": 0,
      "AM": 74,
      "BA": 77,
      "CE": 96,
      "DF": 87,
      "ES": 51,
      "GO": 68,
      "MA": 96,
      "MT": 59,
      "MS": 0,
      "MG": 75,
      "PA": 89,
      "PB": 83,
      "PR": 91,
      "PE": 76,
      "PI": 89,
      "RJ": 82,
      "RN": 77,
      "RS": 82,
      "RO": 0,
      "RR": 0,
      "SC": 84,
      "SP": 67,
      "SE": 93,
      "TO": 46
    }
  },
  {
    "date": "2019-12",
    "states": {
      "AC": 0,
      "AL": 100,
      "AP": 100,
      "AM": 100,
      "BA": 100,
      "CE": 100,
      "DF": 88,
      "ES": 100,
      "GO": 100,
      "MA": 96,
      "MT": 90,
      "MS": 89,
      "MG": 100,
      "PA": 100,
      "PB": 100,
      "PR": 91,
      "PE": 100,
      "PI": 91,
      "RJ": 84,
      "RN": 100,
      "RS": 91,
      "RO": 0,
      "RR": 0,
      "SC": 100,
      "SP": 100,
      "SE": 100,
      "TO": 100
    }
  },
  {
    "date": "2020-01",
    "states": {
      "AC": 0,
      "AL": 81,
      "AP": 0,
      "AM": 73,
      "BA": 79,
      "CE": 84,
      "DF": 88,
      "ES": 69,
      "GO": 61,
      "MA": 95,
      "MT": 100,
      "MS": 100,
      "MG": 77,
      "PA": 75,
      "PB": 84,
      "PR": 89,
      "PE": 80,
      "PI": 100,
      "RJ": 66,
      "RN": 80,
      "RS": 85,
      "RO": 0,
      "RR": 0,
      "SC": 91,
      "SP": 76,
      "SE": 99,
      "TO": 52
    }
  },
  {
    "date": "2020-02",
    "states": {
      "AC": 0,
      "AL": 85,
      "AP": 0,
      "AM": 61,
      "BA": 77,
      "CE": 71,
      "DF": 82,
      "ES": 85,
      "GO": 67,
      "MA": 88,
      "MT": 62,
      "MS": 79,
      "MG": 80,
      "PA": 74,
      "PB": 76,
      "PR": 100,
      "PE": 88,
      "PI": 94,
      "RJ": 100,
      "RN": 77,
      "RS": 100,
      "RO": 0,
      "RR": 0,
      "SC": 89,
      "SP": 72,
      "SE": 97,
      "TO": 84
    }
  },
  {
    "date": "2020-03",
    "states": {
      "AC": 0,
      "AL": 59,
      "AP": 0,
      "AM": 37,
      "BA": 65,
      "CE": 52,
      "DF": 63,
      "ES": 61,
      "GO": 74,
      "MA": 65,
      "MT": 41,
      "MS": 0,
      "MG": 64,
      "PA": 59,
      "PB": 61,
      "PR": 70,
      "PE": 62,
      "PI": 76,
      "RJ": 78,
      "RN": 51,
      "RS": 65,
      "RO": 100,
      "RR": 0,
      "SC": 57,
      "SP": 59,
      "SE": 84,
      "TO": 76
    }
  },
  {
    "date": "2020-04",
    "states": {
      "AC": 0,
      "AL": 39,
      "AP": 0,
      "AM": 31,
      "BA": 44,
      "CE": 39,
      "DF": 45,
      "ES": 0,
      "GO": 41,
      "MA": 48,
      "MT": 64,
      "MS": 0,
      "MG": 45,
      "PA": 52,
      "PB": 42,
      "PR": 49,
      "PE": 46,
      "PI": 38,
      "RJ": 51,
      "RN": 36,
      "RS": 46,
      "RO": 0,
      "RR": 0,
      "SC": 49,
      "SP": 42,
      "SE": 54,
      "TO": 0
    }
  },
  {
    "date": "2020-05",
    "states": {
      "AC": 0,
      "AL": 36,
      "AP": 0,
      "AM": 29,
      "BA": 52,
      "CE": 38,
      "DF": 0,
      "ES": 42,
      "GO": 40,
      "MA": 55,
      "MT": 54,
      "MS": 57,
      "MG": 35,
      "PA": 44,
      "PB": 35,
      "PR": 43,
      "PE": 45,
      "PI": 53,
      "RJ": 41,
      "RN": 35,
      "RS": 44,
      "RO": 65,
      "RR": 0,
      "SC": 36,
      "SP": 34,
      "SE": 48,
      "TO": 0
    }
  },
  {
    "date": "2020-06",
    "states": {
      "AC": 0,
      "AL": 41,
      "AP": 0,
      "AM": 35,
      "BA": 43,
      "CE": 33,
      "DF": 37,
      "ES": 38,
      "GO": 31,
      "MA": 57,
      "MT": 0,
      "MS": 0,
      "MG": 29,
      "PA": 42,
      "PB": 36,
      "PR": 36,
      "PE": 41,
      "PI": 45,
      "RJ": 38,
      "RN": 34,
      "RS": 31,
      "RO": 0,
      "RR": 100,
      "SC": 26,
      "SP": 34,
      "SE": 50,
      "TO": 0
    }
  },
  {
    "date": "2020-07",
    "states": {
      "AC": 0,
      "AL": 37,
      "AP": 0,
      "AM": 41,
      "BA": 42,
      "CE": 37,
      "DF": 0,
      "ES": 38,
      "GO": 30,
      "MA": 56,
      "MT": 0,
      "MS": 0,
      "MG": 30,
      "PA": 43,
      "PB": 36,
      "PR": 44,
      "PE": 47,
      "PI": 44,
      "RJ": 31,
      "RN": 41,
      "RS": 44,
      "RO": 0,
      "RR": 0,
      "SC": 45,
      "SP": 34,
      "SE": 44,
      "TO": 0
    }
  },
  {
    "date": "2020-08",
    "states": {
      "AC": 0,
      "AL": 40,
      "AP": 67,
      "AM": 52,
      "BA": 43,
      "CE": 41,
      "DF": 35,
      "ES": 32,
      "GO": 17,
      "MA": 56,
      "MT": 44,
      "MS": 0,
      "MG": 25,
      "PA": 31,
      "PB": 40,
      "PR": 33,
      "PE": 45,
      "PI": 42,
      "RJ": 38,
      "RN": 33,
      "RS": 27,
      "RO": 0,
      "RR": 0,
      "SC": 40,
      "SP": 26,
      "SE": 51,
      "TO": 0
    }
  },
  {
    "date": "2020-09",
    "states": {
      "AC": 0,
      "AL": 30,
      "AP": 48,
      "AM": 45,
      "BA": 42,
      "CE": 34,
      "DF": 0,
      "ES": 47,
      "GO": 24,
      "MA": 57,
      "MT": 0,
      "MS": 0,
      "MG": 33,
      "PA": 44,
      "PB": 41,
      "PR": 26,
      "PE": 44,
      "PI": 53,
      "RJ": 30,
      "RN": 43,
      "RS": 33,
      "RO": 0,
      "RR": 0,
      "SC": 30,
      "SP": 28,
      "SE": 46,
      "TO": 0
    }
  },
  {
    "date": "2020-10",
    "states": {
      "AC": 0,
      "AL": 38,
      "AP": 0,
      "AM": 43,
      "BA": 40,
      "CE": 34,
      "DF": 0,
      "ES": 0,
      "GO": 0,
      "MA": 39,
      "MT": 52,
      "MS": 0,
      "MG": 27,
      "PA": 35,
      "PB": 39,
      "PR": 27,
      "PE": 44,
      "PI": 44,
      "RJ": 33,
      "RN": 31,
      "RS": 31,
      "RO": 0,
      "RR": 0,
      "SC": 48,
      "SP": 25,
      "SE": 50,
      "TO": 43
    }
  },
  {
    "date": "2020-11",
    "states": {
      "AC": 0,
      "AL": 32,
      "AP": 0,
      "AM": 28,
      "BA": 32,
      "CE": 28,
      "DF": 0,
      "ES": 29,
      "GO": 24,
      "MA": 45,
      "MT": 0,
      "MS": 0,
      "MG": 32,
      "PA": 32,
      "PB": 29,
      "PR": 28,
      "PE": 37,
      "PI": 37,
      "RJ": 35,
      "RN": 22,
      "RS": 36,
      "RO": 0,
      "RR": 0,
      "SC": 29,
      "SP": 30,
      "SE": 38,
      "TO": 0
    }
  },
  {
    "date": "2020-12",
    "states": {
      "AC": 0,
      "AL": 28,
      "AP": 0,
      "AM": 44,
      "BA": 30,
      "CE": 26,
      "DF": 0,
      "ES": 35,
      "GO": 28,
      "MA": 46,
      "MT": 0,
      "MS": 0,
      "MG": 23,
      "PA": 28,
      "PB": 29,
      "PR": 39,
      "PE": 35,
      "PI": 33,
      "RJ": 20,
      "RN": 35,
      "RS": 35,
      "RO": 0,
      "RR": 0,
      "SC": 38,
      "SP": 28,
      "SE": 52,
      "TO": 0
    }
  },
  {
    "date": "2021-01",
    "states": {
      "AC": 0,
      "AL": 27,
      "AP": 0,
      "AM": 0,
      "BA": 28,
      "CE": 22,
      "DF": 0,
      "ES": 0,
      "GO": 25,
      "MA": 34,
      "MT": 0,
      "MS": 0,
      "MG": 25,
      "PA": 32,
      "PB": 30,
      "PR": 32,
      "PE": 34,
      "PI": 35,
      "RJ": 24,
      "RN": 18,
      "RS": 23,
      "RO": 0,
      "RR": 0,
      "SC": 43,
      "SP": 23,
      "SE": 38,
      "TO": 0
    }
  },
  {
    "date": "2021-02",
    "states": {
      "AC": 0,
      "AL": 25,
      "AP": 0,
      "AM": 0,
      "BA": 29,
      "CE": 22,
      "DF": 0,
      "ES": 31,
      "GO": 26,
      "MA": 33,
      "MT": 0,
      "MS": 0,
      "MG": 19,
      "PA": 30,
      "PB": 29,
      "PR": 22,
      "PE": 31,
      "PI": 20,
      "RJ": 30,
      "RN": 21,
      "RS": 23,
      "RO": 0,
      "RR": 0,
      "SC": 25,
      "SP": 23,
      "SE": 37,
      "TO": 0
    }
  },
  {
    "date": "2021-03",
    "states": {
      "AC": 0,
      "AL": 23,
      "AP": 0,
      "AM": 34,
      "BA": 24,
      "CE": 15,
      "DF": 0,
      "ES": 0,
      "GO": 14,
      "MA": 24,
      "MT": 0,
      "MS": 0,
      "MG": 21,
      "PA": 25,
      "PB": 25,
      "PR": 31,
      "PE": 34,
      "PI": 24,
      "RJ": 22,
      "RN": 20,
      "RS": 0,
      "RO": 0,
      "RR": 0,
      "SC": 25,
      "SP": 21,
      "SE": 28,
      "TO": 0
    }
  },
  {
    "date": "2021-04",
    "states": {
      "AC": 0,
      "AL": 22,
      "AP": 0,
      "AM": 29,
      "BA": 24,
      "CE": 19,
      "DF": 0,
      "ES": 0,
      "GO": 24,
      "MA": 23,
      "MT": 0,
      "MS": 0,
      "MG": 22,
      "PA": 26,
      "PB": 20,
      "PR": 18,
      "PE": 29,
      "PI": 15,
      "RJ": 22,
      "RN": 23,
      "RS": 0,
      "RO": 0,
      "RR": 0,
      "SC": 0,
      "SP": 23,
      "SE": 24,
      "TO": 0
    }
  },
  {
    "date": "2021-05",
    "states": {
      "AC": 0,
      "AL": 17,
      "AP": 0,
      "AM": 18,
      "BA": 20,
      "CE": 13,
      "DF": 0,
      "ES": 0,
      "GO": 24,
      "MA": 25,
      "MT": 0,
      "MS": 0,
      "MG": 19,
      "PA": 23,
      "PB": 25,
      "PR": 21,
      "PE": 28,
      "PI": 22,
      "RJ": 12,
      "RN": 22,
      "RS": 0,
      "RO": 0,
      "RR": 0,
      "SC": 24,
      "SP": 18,
      "SE": 25,
      "TO": 0
    }
  },
  {
    "date": "2021-06",
    "states": {
      "AC": 0,
      "AL": 18,
      "AP": 0,
      "AM": 18,
      "BA": 20,
      "CE": 15,
      "DF": 0,
      "ES": 0,
      "GO": 17,
      "MA": 17,
      "MT": 39,
      "MS": 0,
      "MG": 18,
      "PA": 29,
      "PB": 21,
      "PR": 0,
      "PE": 27,
      "PI": 19,
      "RJ": 15,
      "RN": 12,
      "RS": 0,
      "RO": 0,
      "RR": 0,
      "SC": 0,
      "SP": 17,
      "SE": 27,
      "TO": 0
    }
  },
  {
    "date": "2021-07",
    "states": {
      "AC": 0,
      "AL": 18,
      "AP": 0,
      "AM": 27,
      "BA": 20,
      "CE": 13,
      "DF": 0,
      "ES": 35,
      "GO": 18,
      "MA": 21,
      "MT": 0,
      "MS": 0,
      "MG": 19,
      "PA": 18,
      "PB": 19,
      "PR": 0,
      "PE": 27,
      "PI": 20,
      "RJ": 15,
      "RN": 7,
      "RS": 28,
      "RO": 0,
      "RR": 0,
      "SC": 24,
      "SP": 19,
      "SE": 23,
      "TO": 0
    }
  },
  {
    "date": "2021-08",
    "states": {
      "AC": 0,
      "AL": 24,
      "AP": 0,
      "AM": 21,
      "BA": 17,
      "CE": 14,
      "DF": 0,
      "ES": 0,
      "GO": 18,
      "MA": 17,
      "MT": 0,
      "MS": 0,
      "MG": 19,
      "PA": 25,
      "PB": 16,
      "PR": 0,
      "PE": 25,
      "PI": 18,
      "RJ": 17,
      "RN": 11,
      "RS": 0,
      "RO": 0,
      "RR": 0,
      "SC": 23,
      "SP": 16,
      "SE": 24,
      "TO": 0
    }
  },
  {
    "date": "2021-09",
    "states": {
      "AC": 0,
      "AL": 14,
      "AP": 0,
      "AM": 25,
      "BA": 16,
      "CE": 11,
      "DF": 0,
      "ES": 0,
      "GO": 0,
      "MA": 21,
      "MT": 0,
      "MS": 0,
      "MG": 11,
      "PA": 18,
      "PB": 14,
      "PR": 19,
      "PE": 23,
      "PI": 14,
      "RJ": 14,
      "RN": 14,
      "RS": 0,
      "RO": 0,
      "RR": 0,
      "SC": 0,
      "SP": 14,
      "SE": 23,
      "TO": 0
    }
  },
  {
    "date": "2021-10",
    "states": {
      "AC": 0,
      "AL": 15,
      "AP": 0,
      "AM": 25,
      "BA": 18,
      "CE": 12,
      "DF": 0,
      "ES": 0,
      "GO": 0,
      "MA": 12,
      "MT": 0,
      "MS": 0,
      "MG": 12,
      "PA": 20,
      "PB": 16,
      "PR": 0,
      "PE": 28,
      "PI": 17,
      "RJ": 16,
      "RN": 13,
      "RS": 0,
      "RO": 0,
      "RR": 0,
      "SC": 0,
      "SP": 17,
      "SE": 22,
      "TO": 0
    }
  },
  {
    "date": "2021-11",
    "states": {
      "AC": 0,
      "AL": 15,
      "AP": 0,
      "AM": 0,
      "BA": 13,
      "CE": 15,
      "DF": 0,
      "ES": 0,
      "GO": 0,
      "MA": 17,
      "MT": 0,
      "MS": 0,
      "MG": 7,
      "PA": 18,
      "PB": 16,
      "PR": 0,
      "PE": 25,
      "PI": 0,
      "RJ": 16,
      "RN": 12,
      "RS": 0,
      "RO": 0,
      "RR": 0,
      "SC": 0,
      "SP": 13,
      "SE": 25,
      "TO": 0
    }
  },
  {
    "date": "2021-12",
    "states": {
      "AC": 0,
      "AL": 22,
      "AP": 0,
      "AM": 0,
      "BA": 12,
      "CE": 16,
      "DF": 0,
      "ES": 0,
      "GO": 19,
      "MA": 14,
      "MT": 0,
      "MS": 0,
      "MG": 17,
      "PA": 20,
      "PB": 15,
      "PR": 0,
      "PE": 27,
      "PI": 20,
      "RJ": 15,
      "RN": 8,
      "RS": 0,
      "RO": 0,
      "RR": 0,
      "SC": 0,
      "SP": 15,
      "SE": 18,
      "TO": 0
    }
  },
  {
    "date": "2022-01",
    "states": {
      "AC": 0,
      "AL": 15,
      "AP": 0,
      "AM": 0,
      "BA": 14,
      "CE": 12,
      "DF": 0,
      "ES": 0,
      "GO": 0,
      "MA": 14,
      "MT": 0,
      "MS": 0,
      "MG": 14,
      "PA": 15,
      "PB": 15,
      "PR": 0,
      "PE": 24,
      "PI": 16,
      "RJ": 14,
      "RN": 13,
      "RS": 0,
      "RO": 0,
      "RR": 0,
      "SC": 0,
      "SP": 16,
      "SE": 21,
      "TO": 0
    }
  },
  {
    "date": "2022-02",
    "states": {
      "AC": 0,
      "AL": 17,
      "AP": 0,
      "AM": 0,
      "BA": 16,
      "CE": 12,
      "DF": 0,
      "ES": 0,
      "GO": 0,
      "MA": 20,
      "MT": 0,
      "MS": 0,
      "MG": 12,
      "PA": 15,
      "PB": 17,
      "PR": 0,
      "PE": 26,
      "PI": 9,
      "RJ": 13,
      "RN": 14,
      "RS": 0,
      "RO": 0,
      "RR": 0,
      "SC": 21,
      "SP": 11,
      "SE": 27,
      "TO": 0
    }
  },
  {
    "date": "2022-03",
    "states": {
      "AC": 0,
      "AL": 14,
      "AP": 0,
      "AM": 15,
      "BA": 12,
      "CE": 9,
      "DF": 0,
      "ES": 0,
      "GO": 0,
      "MA": 13,
      "MT": 0,
      "MS": 0,
      "MG": 10,
      "PA": 24,
      "PB": 19,
      "PR": 14,
      "PE": 24,
      "PI": 11,
      "RJ": 16,
      "RN": 11,
      "RS": 0,
      "RO": 0,
      "RR": 0,
      "SC": 21,
      "SP": 14,
      "SE": 21,
      "TO": 0
    }
  },
  {
    "date": "2022-04",
    "states": {
      "AC": 0,
      "AL": 17,
      "AP": 0,
      "AM": 0,
      "BA": 13,
      "CE": 9,
      "DF": 0,
      "ES": 0,
      "GO": 14,
      "MA": 13,
      "MT": 0,
      "MS": 0,
      "MG": 8,
      "PA": 11,
      "PB": 19,
      "PR": 0,
      "PE": 25,
      "PI": 12,
      "RJ": 13,
      "RN": 12,
      "RS": 0,
      "RO": 0,
      "RR": 0,
      "SC": 22,
      "SP": 13,
      "SE": 20,
      "TO": 0
    }
  },
  {
    "date": "2022-05",
    "states": {
      "AC": 0,
      "AL": 13,
      "AP": 0,
      "AM": 0,
      "BA": 9,
      "CE": 8,
      "DF": 0,
      "ES": 0,
      "GO": 15,
      "MA": 13,
      "MT": 0,
      "MS": 0,
      "MG": 8,
      "PA": 11,
      "PB": 14,
      "PR": 19,
      "PE": 19,
      "PI": 17,
      "RJ": 10,
      "RN": 9,
      "RS": 0,
      "RO": 0,
      "RR": 0,
      "SC": 0,
      "SP": 11,
      "SE": 15,
      "TO": 0
    }
  },
  {
    "date": "2022-06",
    "states": {
      "AC": 0,
      "AL": 15,
      "AP": 0,
      "AM": 0,
      "BA": 12,
      "CE": 10,
      "DF": 0,
      "ES": 0,
      "GO": 0,
      "MA": 17,
      "MT": 0,
      "MS": 0,
      "MG": 9,
      "PA": 11,
      "PB": 16,
      "PR": 0,
      "PE": 22,
      "PI": 9,
      "RJ": 12,
      "RN": 7,
      "RS": 0,
      "RO": 0,
      "RR": 0,
      "SC": 23,
      "SP": 12,
      "SE": 15,
      "TO": 0
    }
  },
  {
    "date": "2022-07",
    "states": {
      "AC": 0,
      "AL": 13,
      "AP": 0,
      "AM": 20,
      "BA": 11,
      "CE": 14,
      "DF": 0,
      "ES": 0,
      "GO": 21,
      "MA": 13,
      "MT": 0,
      "MS": 0,
      "MG": 7,
      "PA": 13,
      "PB": 15,
      "PR": 0,
      "PE": 26,
      "PI": 9,
      "RJ": 0,
      "RN": 14,
      "RS": 17,
      "RO": 0,
      "RR": 0,
      "SC": 0,
      "SP": 15,
      "SE": 15,
      "TO": 0
    }
  },
  {
    "date": "2022-08",
    "states": {
      "AC": 0,
      "AL": 15,
      "AP": 0,
      "AM": 15,
      "BA": 10,
      "CE": 13,
      "DF": 0,
      "ES": 0,
      "GO": 12,
      "MA": 14,
      "MT": 0,
      "MS": 0,
      "MG": 9,
      "PA": 17,
      "PB": 18,
      "PR": 14,
      "PE": 26,
      "PI": 14,
      "RJ": 13,
      "RN": 13,
      "RS": 14,
      "RO": 0,
      "RR": 0,
      "SC": 0,
      "SP": 10,
      "SE": 19,
      "TO": 0
    }
  },
  {
    "date": "2022-09",
    "states": {
      "AC": 0,
      "AL": 13,
      "AP": 0,
      "AM": 0,
      "BA": 9,
      "CE": 12,
      "DF": 0,
      "ES": 0,
      "GO": 13,
      "MA": 14,
      "MT": 0,
      "MS": 0,
      "MG": 9,
      "PA": 8,
      "PB": 19,
      "PR": 0,
      "PE": 29,
      "PI": 13,
      "RJ": 11,
      "RN": 14,
      "RS": 0,
      "RO": 0,
      "RR": 0,
      "SC": 0,
      "SP": 9,
      "SE": 20,
      "TO": 0
    }
  },
  {
    "date": "2022-10",
    "states": {
      "AC": 0,
      "AL": 13,
      "AP": 0,
      "AM": 0,
      "BA": 9,
      "CE": 10,
      "DF": 0,
      "ES": 0,
      "GO": 0,
      "MA": 10,
      "MT": 0,
      "MS": 0,
      "MG": 10,
      "PA": 11,
      "PB": 16,
      "PR": 0,
      "PE": 19,
      "PI": 0,
      "RJ": 10,
      "RN": 9,
      "RS": 0,
      "RO": 0,
      "RR": 0,
      "SC": 0,
      "SP": 8,
      "SE": 15,
      "TO": 0
    }
  },
  {
    "date": "2022-11",
    "states": {
      "AC": 0,
      "AL": 8,
      "AP": 0,
      "AM": 0,
      "BA": 9,
      "CE": 6,
      "DF": 0,
      "ES": 0,
      "GO": 0,
      "MA": 8,
      "MT": 0,
      "MS": 0,
      "MG": 4,
      "PA": 0,
      "PB": 11,
      "PR": 0,
      "PE": 17,
      "PI": 8,
      "RJ": 0,
      "RN": 8,
      "RS": 0,
      "RO": 0,
      "RR": 0,
      "SC": 0,
      "SP": 6,
      "SE": 12,
      "TO": 0
    }
  },
  {
    "date": "2022-12",
    "states": {
      "AC": 0,
      "AL": 11,
      "AP": 0,
      "AM": 0,
      "BA": 7,
      "CE": 10,
      "DF": 0,
      "ES": 0,
      "GO": 0,
      "MA": 0,
      "MT": 0,
      "MS": 0,
      "MG": 0,
      "PA": 0,
      "PB": 12,
      "PR": 20,
      "PE": 19,
      "PI": 0,
      "RJ": 12,
      "RN": 9,
      "RS": 0,
      "RO": 0,
      "RR": 0,
      "SC": 0,
      "SP": 10,
      "SE": 13,
      "TO": 0
    }
  },
  {
    "date": "2023-01",
    "states": {
      "AC": 0,
      "AL": 9,
      "AP": 0,
      "AM": 0,
      "BA": 6,
      "CE": 5,
      "DF": 0,
      "ES": 0,
      "GO": 0,
      "MA": 8,
      "MT": 0,
      "MS": 0,
      "MG": 5,
      "PA": 0,
      "PB": 13,
      "PR": 16,
      "PE": 18,
      "PI": 0,
      "RJ": 0,
      "RN": 10,
      "RS": 0,
      "RO": 0,
      "RR": 0,
      "SC": 0,
      "SP": 11,
      "SE": 9,
      "TO": 0
    }
  },
  {
    "date": "2023-02",
    "states": {
      "AC": 0,
      "AL": 11,
      "AP": 0,
      "AM": 16,
      "BA": 7,
      "CE": 4,
      "DF": 0,
      "ES": 0,
      "GO": 0,
      "MA": 7,
      "MT": 0,
      "MS": 0,
      "MG": 6,
      "PA": 16,
      "PB": 10,
      "PR": 0,
      "PE": 20,
      "PI": 0,
      "RJ": 15,
      "RN": 7,
      "RS": 0,
      "RO": 0,
      "RR": 0,
      "SC": 0,
      "SP": 10,
      "SE": 17,
      "TO": 0
    }
  },
  {
    "date": "2023-03",
    "states": {
      "AC": 0,
      "AL": 7,
      "AP": 0,
      "AM": 0,
      "BA": 4,
      "CE": 5,
      "DF": 0,
      "ES": 0,
      "GO": 0,
      "MA": 0,
      "MT": 0,
      "MS": 0,
      "MG": 6,
      "PA": 11,
      "PB": 8,
      "PR": 0,
      "PE": 15,
      "PI": 0,
      "RJ": 0,
      "RN": 6,
      "RS": 0,
      "RO": 0,
      "RR": 0,
      "SC": 0,
      "SP": 6,
      "SE": 7,
      "TO": 0
    }
  },
  {
    "date": "2023-04",
    "states": {
      "AC": 0,
      "AL": 8,
      "AP": 0,
      "AM": 0,
      "BA": 6,
      "CE": 7,
      "DF": 0,
      "ES": 0,
      "GO": 0,
      "MA": 8,
      "MT": 0,
      "MS": 0,
      "MG": 14,
      "PA": 9,
      "PB": 10,
      "PR": 14,
      "PE": 13,
      "PI": 0,
      "RJ": 17,
      "RN": 8,
      "RS": 0,
      "RO": 0,
      "RR": 0,
      "SC": 0,
      "SP": 20,
      "SE": 8,
      "TO": 0
    }
  },
  {
    "date": "2023-05",
    "states": {
      "AC": 0,
      "AL": 6,
      "AP": 0,
      "AM": 0,
      "BA": 5,
      "CE": 5,
      "DF": 0,
      "ES": 0,
      "GO": 0,
      "MA": 8,
      "MT": 0,
      "MS": 0,
      "MG": 0,
      "PA": 0,
      "PB": 9,
      "PR": 0,
      "PE": 15,
      "PI": 0,
      "RJ": 0,
      "RN": 8,
      "RS": 0,
      "RO": 0,
      "RR": 0,
      "SC": 0,
      "SP": 8,
      "SE": 10,
      "TO": 0
    }
  },
  {
    "date": "2023-06",
    "states": {
      "AC": 0,
      "AL": 4,
      "AP": 0,
      "AM": 0,
      "BA": 3,
      "CE": 8,
      "DF": 0,
      "ES": 0,
      "GO": 0,
      "MA": 0,
      "MT": 0,
      "MS": 0,
      "MG": 0,
      "PA": 12,
      "PB": 9,
      "PR": 0,
      "PE": 13,
      "PI": 0,
      "RJ": 0,
      "RN": 7,
      "RS": 0,
      "RO": 0,
      "RR": 0,
      "SC": 0,
      "SP": 9,
      "SE": 0,
      "TO": 0
    }
  },
  {
    "date": "2023-07",
    "states": {
      "AC": 0,
      "AL": 7,
      "AP": 0,
      "AM": 0,
      "BA": 4,
      "CE": 6,
      "DF": 0,
      "ES": 0,
      "GO": 0,
      "MA": 0,
      "MT": 0,
      "MS": 0,
      "MG": 8,
      "PA": 9,
      "PB": 9,
      "PR": 0,
      "PE": 12,
      "PI": 0,
      "RJ": 0,
      "RN": 0,
      "RS": 0,
      "RO": 0,
      "RR": 0,
      "SC": 0,
      "SP": 8,
      "SE": 12,
      "TO": 0
    }
  },
  {
    "date": "2023-08",
    "states": {
      "AC": 0,
      "AL": 8,
      "AP": 0,
      "AM": 0,
      "BA": 7,
      "CE": 8,
      "DF": 0,
      "ES": 0,
      "GO": 0,
      "MA": 7,
      "MT": 0,
      "MS": 0,
      "MG": 8,
      "PA": 12,
      "PB": 12,
      "PR": 0,
      "PE": 22,
      "PI": 0,
      "RJ": 10,
      "RN": 9,
      "RS": 20,
      "RO": 0,
      "RR": 0,
      "SC": 0,
      "SP": 10,
      "SE": 0,
      "TO": 0
    }
  },
  {
    "date": "2023-09",
    "states": {
      "AC": 0,
      "AL": 7,
      "AP": 0,
      "AM": 17,
      "BA": 7,
      "CE": 7,
      "DF": 0,
      "ES": 0,
      "GO": 0,
      "MA": 8,
      "MT": 0,
      "MS": 0,
      "MG": 7,
      "PA": 9,
      "PB": 11,
      "PR": 0,
      "PE": 20,
      "PI": 13,
      "RJ": 0,
      "RN": 6,
      "RS": 0,
      "RO": 0,
      "RR": 0,
      "SC": 0,
      "SP": 8,
      "SE": 10,
      "TO": 0
    }
  },
  {
    "date": "2023-10",
    "states": {
      "AC": 0,
      "AL": 13,
      "AP": 0,
      "AM": 0,
      "BA": 7,
      "CE": 5,
      "DF": 0,
      "ES": 0,
      "GO": 0,
      "MA": 0,
      "MT": 45,
      "MS": 0,
      "MG": 7,
      "PA": 15,
      "PB": 7,
      "PR": 0,
      "PE": 19,
      "PI": 0,
      "RJ": 0,
      "RN": 7,
      "RS": 0,
      "RO": 0,
      "RR": 0,
      "SC": 0,
      "SP": 9,
      "SE": 11,
      "TO": 0
    }
  },
  {
    "date": "2023-11",
    "states": {
      "AC": 0,
      "AL": 9,
      "AP": 0,
      "AM": 0,
      "BA": 4,
      "CE": 6,
      "DF": 0,
      "ES": 0,
      "GO": 15,
      "MA": 6,
      "MT": 0,
      "MS": 0,
      "MG": 0,
      "PA": 11,
      "PB": 12,
      "PR": 0,
      "PE": 19,
      "PI": 0,
      "RJ": 10,
      "RN": 5,
      "RS": 0,
      "RO": 0,
      "RR": 0,
      "SC": 0,
      "SP": 9,
      "SE": 17,
      "TO": 0
    }
  },
  {
    "date": "2023-12",
    "states": {
      "AC": 0,
      "AL": 11,
      "AP": 0,
      "AM": 0,
      "BA": 8,
      "CE": 5,
      "DF": 0,
      "ES": 0,
      "GO": 0,
      "MA": 14,
      "MT": 0,
      "MS": 0,
      "MG": 7,
      "PA": 0,
      "PB": 14,
      "PR": 0,
      "PE": 22,
      "PI": 0,
      "RJ": 19,
      "RN": 6,
      "RS": 0,
      "RO": 0,
      "RR": 0,
      "SC": 0,
      "SP": 11,
      "SE": 18,
      "TO": 0
    }
  },
  {
    "date": "2024-01",
    "states": {
      "AC": 0,
      "AL": 8,
      "AP": 0,
      "AM": 0,
      "BA": 8,
      "CE": 7,
      "DF": 0,
      "ES": 0,
      "GO": 0,
      "MA": 9,
      "MT": 0,
      "MS": 0,
      "MG": 6,
      "PA": 0,
      "PB": 14,
      "PR": 0,
      "PE": 22,
      "PI": 0,
      "RJ": 10,
      "RN": 9,
      "RS": 0,
      "RO": 0,
      "RR": 0,
      "SC": 0,
      "SP": 11,
      "SE": 12,
      "TO": 0
    }
  },
  {
    "date": "2024-02",
    "states": {
      "AC": 0,
      "AL": 10,
      "AP": 0,
      "AM": 0,
      "BA": 8,
      "CE": 5,
      "DF": 0,
      "ES": 0,
      "GO": 17,
      "MA": 0,
      "MT": 0,
      "MS": 0,
      "MG": 0,
      "PA": 17,
      "PB": 14,
      "PR": 0,
      "PE": 26,
      "PI": 0,
      "RJ": 0,
      "RN": 8,
      "RS": 0,
      "RO": 0,
      "RR": 0,
      "SC": 0,
      "SP": 10,
      "SE": 15,
      "TO": 0
    }
  },
  {
    "date": "2024-03",
    "states": {
      "AC": 0,
      "AL": 12,
      "AP": 0,
      "AM": 0,
      "BA": 5,
      "CE": 11,
      "DF": 0,
      "ES": 0,
      "GO": 0,
      "MA": 10,
      "MT": 0,
      "MS": 0,
      "MG": 7,
      "PA": 10,
      "PB": 13,
      "PR": 0,
      "PE": 28,
      "PI": 0,
      "RJ": 21,
      "RN": 7,
      "RS": 0,
      "RO": 0,
      "RR": 0,
      "SC": 24,
      "SP": 6,
      "SE": 8,
      "TO": 0
    }
  },
  {
    "date": "2024-04",
    "states": {
      "AC": 0,
      "AL": 8,
      "AP": 0,
      "AM": 0,
      "BA": 5,
      "CE": 6,
      "DF": 0,
      "ES": 0,
      "GO": 0,
      "MA": 10,
      "MT": 0,
      "MS": 0,
      "MG": 0,
      "PA": 0,
      "PB": 15,
      "PR": 0,
      "PE": 21,
      "PI": 0,
      "RJ": 0,
      "RN": 6,
      "RS": 0,
      "RO": 0,
      "RR": 0,
      "SC": 0,
      "SP": 10,
      "SE": 12,
      "TO": 0
    }
  },
  {
    "date": "2024-05",
    "states": {
      "AC": 0,
      "AL": 9,
      "AP": 0,
      "AM": 0,
      "BA": 7,
      "CE": 8,
      "DF": 0,
      "ES": 0,
      "GO": 0,
      "MA": 9,
      "MT": 0,
      "MS": 0,
      "MG": 13,
      "PA": 0,
      "PB": 14,
      "PR": 0,
      "PE": 28,
      "PI": 0,
      "RJ": 0,
      "RN": 8,
      "RS": 0,
      "RO": 0,
      "RR": 0,
      "SC": 0,
      "SP": 11,
      "SE": 13,
      "TO": 0
    }
  },
  {
    "date": "2024-06",
    "states": {
      "AC": 0,
      "AL": 8,
      "AP": 0,
      "AM": 0,
      "BA": 9,
      "CE": 7,
      "DF": 0,
      "ES": 0,
      "GO": 0,
      "MA": 12,
      "MT": 0,
      "MS": 0,
      "MG": 8,
      "PA": 15,
      "PB": 12,
      "PR": 0,
      "PE": 29,
      "PI": 0,
      "RJ": 11,
      "RN": 11,
      "RS": 0,
      "RO": 0,
      "RR": 0,
      "SC": 0,
      "SP": 11,
      "SE": 8,
      "TO": 0
    }
  },
  {
    "date": "2024-07",
    "states": {
      "AC": 0,
      "AL": 14,
      "AP": 0,
      "AM": 0,
      "BA": 5,
      "CE": 6,
      "DF": 0,
      "ES": 0,
      "GO": 0,
      "MA": 13,
      "MT": 0,
      "MS": 0,
      "MG": 0,
      "PA": 12,
      "PB": 12,
      "PR": 0,
      "PE": 24,
      "PI": 0,
      "RJ": 20,
      "RN": 8,
      "RS": 0,
      "RO": 0,
      "RR": 0,
      "SC": 26,
      "SP": 7,
      "SE": 9,
      "TO": 0
    }
  },
  {
    "date": "2024-08",
    "states": {
      "AC": 0,
      "AL": 13,
      "AP": 0,
      "AM": 0,
      "BA": 7,
      "CE": 9,
      "DF": 0,
      "ES": 0,
      "GO": 0,
      "MA": 9,
      "MT": 0,
      "MS": 0,
      "MG": 12,
      "PA": 12,
      "PB": 15,
      "PR": 0,
      "PE": 30,
      "PI": 0,
      "RJ": 0,
      "RN": 0,
      "RS": 0,
      "RO": 0,
      "RR": 0,
      "SC": 0,
      "SP": 12,
      "SE": 14,
      "TO": 0
    }
  },
  {
    "date": "2024-09",
    "states": {
      "AC": 0,
      "AL": 11,
      "AP": 0,
      "AM": 0,
      "BA": 7,
      "CE": 7,
      "DF": 0,
      "ES": 0,
      "GO": 0,
      "MA": 11,
      "MT": 0,
      "MS": 0,
      "MG": 9,
      "PA": 12,
      "PB": 12,
      "PR": 0,
      "PE": 31,
      "PI": 11,
      "RJ": 15,
      "RN": 12,
      "RS": 0,
      "RO": 0,
      "RR": 0,
      "SC": 0,
      "SP": 11,
      "SE": 11,
      "TO": 0
    }
  },
  {
    "date": "2024-10",
    "states": {
      "AC": 0,
      "AL": 11,
      "AP": 0,
      "AM": 0,
      "BA": 6,
      "CE": 7,
      "DF": 0,
      "ES": 0,
      "GO": 0,
      "MA": 9,
      "MT": 0,
      "MS": 0,
      "MG": 7,
      "PA": 0,
      "PB": 14,
      "PR": 0,
      "PE": 23,
      "PI": 0,
      "RJ": 14,
      "RN": 10,
      "RS": 0,
      "RO": 0,
      "RR": 0,
      "SC": 0,
      "SP": 10,
      "SE": 9,
      "TO": 0
    }
  },
  {
    "date": "2024-11",
    "states": {
      "AC": 0,
      "AL": 9,
      "AP": 0,
      "AM": 20,
      "BA": 7,
      "CE": 7,
      "DF": 0,
      "ES": 0,
      "GO": 0,
      "MA": 9,
      "MT": 0,
      "MS": 0,
      "MG": 6,
      "PA": 17,
      "PB": 16,
      "PR": 0,
      "PE": 27,
      "PI": 0,
      "RJ": 0,
      "RN": 8,
      "RS": 0,
      "RO": 0,
      "RR": 0,
      "SC": 0,
      "SP": 10,
      "SE": 11,
      "TO": 0
    }
  },
  {
    "date": "2024-12",
    "states": {
      "AC": 0,
      "AL": 14,
      "AP": 0,
      "AM": 0,
      "BA": 5,
      "CE": 9,
      "DF": 0,
      "ES": 0,
      "GO": 0,
      "MA": 0,
      "MT": 0,
      "MS": 0,
      "MG": 7,
      "PA": 13,
      "PB": 15,
      "PR": 0,
      "PE": 30,
      "PI": 0,
      "RJ": 13,
      "RN": 11,
      "RS": 0,
      "RO": 0,
      "RR": 0,
      "SC": 0,
      "SP": 9,
      "SE": 0,
      "TO": 0
    }
  },
  {
    "date": "2025-01",
    "states": {
      "AC": 0,
      "AL": 8,
      "AP": 0,
      "AM": 0,
      "BA": 7,
      "CE": 7,
      "DF": 0,
      "ES": 0,
      "GO": 0,
      "MA": 0,
      "MT": 0,
      "MS": 0,
      "MG": 6,
      "PA": 0,
      "PB": 15,
      "PR": 0,
      "PE": 21,
      "PI": 0,
      "RJ": 13,
      "RN": 0,
      "RS": 0,
      "RO": 0,
      "RR": 0,
      "SC": 0,
      "SP": 11,
      "SE": 13,
      "TO": 0
    }
  },
  {
    "date": "2025-02",
    "states": {
      "AC": 0,
      "AL": 8,
      "AP": 0,
      "AM": 0,
      "BA": 5,
      "CE": 10,
      "DF": 0,
      "ES": 0,
      "GO": 0,
      "MA": 8,
      "MT": 0,
      "MS": 0,
      "MG": 0,
      "PA": 0,
      "PB": 15,
      "PR": 0,
      "PE": 25,
      "PI": 0,
      "RJ": 0,
      "RN": 12,
      "RS": 22,
      "RO": 0,
      "RR": 0,
      "SC": 0,
      "SP": 8,
      "SE": 10,
      "TO": 0
    }
  },
  {
    "date": "2025-03",
    "states": {
      "AC": 0,
      "AL": 11,
      "AP": 0,
      "AM": 0,
      "BA": 5,
      "CE": 6,
      "DF": 0,
      "ES": 0,
      "GO": 0,
      "MA": 0,
      "MT": 0,
      "MS": 0,
      "MG": 8,
      "PA": 11,
      "PB": 12,
      "PR": 0,
      "PE": 30,
      "PI": 0,
      "RJ": 0,
      "RN": 0,
      "RS": 0,
      "RO": 0,
      "RR": 0,
      "SC": 0,
      "SP": 6,
      "SE": 9,
      "TO": 0
    }
  },
  {
    "date": "2025-04",
    "states": {
      "AC": 0,
      "AL": 12,
      "AP": 0,
      "AM": 0,
      "BA": 5,
      "CE": 4,
      "DF": 0,
      "ES": 0,
      "GO": 0,
      "MA": 0,
      "MT": 0,
      "MS": 0,
      "MG": 10,
      "PA": 0,
      "PB": 11,
      "PR": 0,
      "PE": 31,
      "PI": 0,
      "RJ": 0,
      "RN": 8,
      "RS": 0,
      "RO": 0,
      "RR": 0,
      "SC": 0,
      "SP": 11,
      "SE": 10,
      "TO": 0
    }
  },
  {
    "date": "2025-05",
    "states": {
      "AC": 0,
      "AL": 7,
      "AP": 0,
      "AM": 0,
      "BA": 6,
      "CE": 7,
      "DF": 0,
      "ES": 0,
      "GO": 0,
      "MA": 0,
      "MT": 0,
      "MS": 0,
      "MG": 7,
      "PA": 11,
      "PB": 17,
      "PR": 0,
      "PE": 25,
      "PI": 0,
      "RJ": 15,
      "RN": 0,
      "RS": 0,
      "RO": 0,
      "RR": 0,
      "SC": 0,
      "SP": 8,
      "SE": 0,
      "TO": 0
    }
  },
  {
    "date": "2025-06",
    "states": {
      "AC": 0,
      "AL": 11,
      "AP": 0,
      "AM": 0,
      "BA": 5,
      "CE": 6,
      "DF": 0,
      "ES": 0,
      "GO": 0,
      "MA": 0,
      "MT": 0,
      "MS": 0,
      "MG": 6,
      "PA": 12,
      "PB": 17,
      "PR": 0,
      "PE": 23,
      "PI": 0,
      "RJ": 0,
      "RN": 0,
      "RS": 0,
      "RO": 0,
      "RR": 0,
      "SC": 0,
      "SP": 10,
      "SE": 0,
      "TO": 0
    }
  },
  {
    "date": "2025-07",
    "states": {
      "AC": 0,
      "AL": 10,
      "AP": 0,
      "AM": 0,
      "BA": 5,
      "CE": 5,
      "DF": 0,
      "ES": 0,
      "GO": 0,
      "MA": 0,
      "MT": 0,
      "MS": 0,
      "MG": 6,
      "PA": 0,
      "PB": 11,
      "PR": 0,
      "PE": 26,
      "PI": 0,
      "RJ": 0,
      "RN": 6,
      "RS": 0,
      "RO": 0,
      "RR": 0,
      "SC": 0,
      "SP": 8,
      "SE": 13,
      "TO": 0
    }
  },
  {
    "date": "2025-08",
    "states": {
      "AC": 0,
      "AL": 12,
      "AP": 0,
      "AM": 22,
      "BA": 8,
      "CE": 8,
      "DF": 0,
      "ES": 0,
      "GO": 22,
      "MA": 0,
      "MT": 0,
      "MS": 0,
      "MG": 10,
      "PA": 0,
      "PB": 13,
      "PR": 0,
      "PE": 26,
      "PI": 0,
      "RJ": 0,
      "RN": 7,
      "RS": 0,
      "RO": 0,
      "RR": 0,
      "SC": 0,
      "SP": 10,
      "SE": 8,
      "TO": 0
    }
  },
  {
    "date": "2025-09",
    "states": {
      "AC": 0,
      "AL": 11,
      "AP": 0,
      "AM": 0,
      "BA": 6,
      "CE": 6,
      "DF": 0,
      "ES": 0,
      "GO": 0,
      "MA": 9,
      "MT": 0,
      "MS": 0,
      "MG": 7,
      "PA": 11,
      "PB": 12,
      "PR": 0,
      "PE": 27,
      "PI": 0,
      "RJ": 21,
      "RN": 10,
      "RS": 0,
      "RO": 0,
      "RR": 0,
      "SC": 0,
      "SP": 7,
      "SE": 0,
      "TO": 0
    }
  },
  {
    "date": "2025-10",
    "states": {
      "AC": 0,
      "AL": 9,
      "AP": 0,
      "AM": 0,
      "BA": 6,
      "CE": 6,
      "DF": 0,
      "ES": 0,
      "GO": 0,
      "MA": 0,
      "MT": 0,
      "MS": 0,
      "MG": 6,
      "PA": 10,
      "PB": 15,
      "PR": 0,
      "PE": 27,
      "PI": 0,
      "RJ": 0,
      "RN": 0,
      "RS": 0,
      "RO": 0,
      "RR": 0,
      "SC": 0,
      "SP": 10,
      "SE": 10,
      "TO": 0
    }
  },
  {
    "date": "2025-11",
    "states": {
      "AC": 0,
      "AL": 9,
      "AP": 0,
      "AM": 0,
      "BA": 8,
      "CE": 6,
      "DF": 0,
      "ES": 0,
      "GO": 0,
      "MA": 0,
      "MT": 0,
      "MS": 0,
      "MG": 11,
      "PA": 13,
      "PB": 17,
      "PR": 0,
      "PE": 29,
      "PI": 11,
      "RJ": 17,
      "RN": 0,
      "RS": 0,
      "RO": 0,
      "RR": 0,
      "SC": 0,
      "SP": 15,
      "SE": 0,
      "TO": 0
    }
  },
  {
    "date": "2025-12",
    "states": {
      "AC": 0,
      "AL": 16,
      "AP": 0,
      "AM": 0,
      "BA": 11,
      "CE": 9,
      "DF": 0,
      "ES": 0,
      "GO": 18,
      "MA": 12,
      "MT": 0,
      "MS": 0,
      "MG": 38,
      "PA": 14,
      "PB": 18,
      "PR": 37,
      "PE": 34,
      "PI": 0,
      "RJ": 43,
      "RN": 12,
      "RS": 35,
      "RO": 0,
      "RR": 0,
      "SC": 49,
      "SP": 39,
      "SE": 8,
      "TO": 0
    }
  }
]